{
  "version": 1,
  "preset_name": "default_smyrator",
  "com_port": "",
  "settings": {
    "wheel_d_cm": 5.0,
    "rot_duration_s": 2.5,
    "interval_s": 0.25,
    "repeats": 1,
    "scramble": false,
    "seed": "",
    "rot_microsteps": 128,
    "hybrid_en": true,
    "stealth_max": 8.0,
    "spread_min": 8.0,
    "rot_i_stealth_mA": 350,
    "rot_i_spread_mA": 400,
    "lin_i_mA": 500,
    "spread_preset": 1,
    "dither_en": true,
    "dither_min": 8.0,
    "dither_amp": 0.0035,
    "dither_hz": 30.0,
    "dither_us": 2000,
    "lin_steps_mm": 14.1593,
    "lin_home_cm_s": 3.0,
    "lin_move_cm_s": 5.0,
    "lin_offset_cm0": 0.5,
    "lin_halfrev_cm": 11.3
  },
  "positions": [],
  "rotary_tokens": [],
  "order": []
}
